huscy/subject_contact_history/__init__.py
huscy/subject_contact_history/apps.py
huscy/subject_contact_history/models.py
huscy/subject_contact_history/serializer.py
huscy/subject_contact_history/services.py
huscy/subject_contact_history/urls.py
huscy/subject_contact_history/views.py
huscy/subject_contact_history/migrations/0001_initial.py
huscy/subject_contact_history/migrations/__init__.py
huscy_subject_contact_history-1.1.0.dist-info/METADATA
huscy_subject_contact_history-1.1.0.dist-info/WHEEL
huscy_subject_contact_history-1.1.0.dist-info/top_level.txt
huscy_subject_contact_history-1.1.0.dist-info/RECORD
