Metadata-Version: 2.4
Name: huscy.subject_contact_history
Version: 1.1.0
Author: Stefan Bunde
Author-email: stefanbunde+git@posteo.de
License: AGPLv3+
Classifier: Development Status :: 3 - Alpha
Classifier: License :: OSI Approved :: GNU Affero General Public License v3 or later (AGPLv3+)
Classifier: Operating System :: OS Independent
Classifier: Programming Language :: Python
Classifier: Programming Language :: Python :: 3
Classifier: Programming Language :: Python :: 3 :: Only
Classifier: Programming Language :: Python :: 3.8
Classifier: Programming Language :: Python :: 3.9
Classifier: Programming Language :: Python :: 3.10
Classifier: Programming Language :: Python :: 3.11
Classifier: Programming Language :: Python :: 3.12
Classifier: Programming Language :: Python :: 3.13
Classifier: Framework :: Django
Classifier: Framework :: Django :: 4.2
Classifier: Framework :: Django :: 5.1
Classifier: Framework :: Django :: 5.2
Requires-Dist: huscy.projects
Requires-Dist: huscy.pseudonyms
Requires-Dist: huscy.subjects
Provides-Extra: development
Requires-Dist: psycopg2-binary; extra == "development"
Provides-Extra: testing
Requires-Dist: tox; extra == "testing"
Requires-Dist: watchdog; extra == "testing"
Dynamic: author
Dynamic: author-email
Dynamic: classifier
Dynamic: license
Dynamic: provides-extra
Dynamic: requires-dist
